{
  "appInfo" : {
    "build" : "223.8617.48",
    "buildDate" : "2023-01-24T13:40:28.202Z[UTC]",
    "productCode" : "PC",
    "generated" : "2023-02-16T11:30:21.0332099Z",
    "os" : "Windows 10 10.0",
    "runtime" : "JetBrains s.r.o. 17.0.5 17.0.5+1-b653.25"
  },
  "runtimeInfo" : {
    "maxMemory" : 1065353216,
    "numberOfProcessors" : 4,
    "maxNumberOfIndexingThreads" : 3,
    "maxSizeOfFileForIntelliSense" : 2560000,
    "maxSizeOfFileForContentLoading" : 20971520
  },
  "projectIndexingHistory" : {
    "projectName" : "pythonProject13",
    "times" : {
      "indexingReason" : "On refresh of 8604 files",
      "scanningType" : "REFRESH",
      "totalUpdatingTime" : 40814500200,
      "indexingTime" : 40819856300,
      "contentLoadingVisibleTime" : 3540512368,
      "creatingIteratorsTime" : 0,
      "scanFilesTime" : 598055700,
      "pushPropertiesTime" : 0,
      "indexExtensionsTime" : 0,
      "isAppliedAllValuesSeparately" : true,
      "separateApplyingIndexesVisibleTime" : 19884324847,
      "updatingStart" : "2023-02-16T11:29:40.2133536Z",
      "updatingEnd" : "2023-02-16T11:30:21.0332099Z",
      "totalSuspendedTime" : 0,
      "wasInterrupted" : false
    },
    "fileCount" : {
      "numberOfFileProviders" : 1,
      "numberOfScannedFiles" : 8604,
      "numberOfFilesIndexedByInfrastructureExtensionsDuringScan" : 0,
      "numberOfFilesScheduledForIndexingAfterScan" : 8604,
      "numberOfFilesIndexedByInfrastructureExtensionsDuringIndexingStage" : 0,
      "numberOfFilesIndexedWithLoadingContent" : 8604
    },
    "totalStatsPerFileType" : [ {
      "fileType" : "UNKNOWN",
      "partOfTotalProcessingTime" : {
        "part" : 2315810900,
        "total" : 2329470700
      },
      "partOfTotalContentLoadingTime" : {
        "part" : 201959500,
        "total" : 202078600
      },
      "totalNumberOfFiles" : 8603,
      "totalFilesSize" : 0,
      "totalProcessingSpeed" : {
        "totalBytes" : 0,
        "totalTime" : 2315810900
      },
      "biggestContributors" : [ {
        "providerName" : "Refreshed files",
        "numberOfFiles" : 8603,
        "totalFilesSize" : 0,
        "partOfTotalProcessingTimeOfThisFileType" : {
          "part" : 2315810900,
          "total" : 2315810900
        }
      } ]
    }, {
      "fileType" : "Python",
      "partOfTotalProcessingTime" : {
        "part" : 13659800,
        "total" : 2329470700
      },
      "partOfTotalContentLoadingTime" : {
        "part" : 119100,
        "total" : 202078600
      },
      "totalNumberOfFiles" : 1,
      "totalFilesSize" : 2070,
      "totalProcessingSpeed" : {
        "totalBytes" : 2070,
        "totalTime" : 13659800
      },
      "biggestContributors" : [ {
        "providerName" : "Refreshed files",
        "numberOfFiles" : 1,
        "totalFilesSize" : 2070,
        "partOfTotalProcessingTimeOfThisFileType" : {
          "part" : 13659800,
          "total" : 13659800
        }
      } ]
    } ],
    "totalStatsPerIndexer" : [ {
      "indexId" : "Stubs",
      "partOfTotalIndexingTime" : {
        "part" : 8387300,
        "total" : 8537600
      },
      "totalNumberOfFiles" : 1,
      "totalNumberOfFilesIndexedByExtensions" : 0,
      "totalFilesSize" : 2070,
      "indexValueChangerEvaluationSpeed" : {
        "totalBytes" : 2070,
        "totalTime" : 8387300
      },
      "snapshotInputMappingStats" : {
        "totalRequests" : 0,
        "totalMisses" : 0,
        "totalHits" : 0
      }
    }, {
      "indexId" : "IdIndex",
      "partOfTotalIndexingTime" : {
        "part" : 84700,
        "total" : 8537600
      },
      "totalNumberOfFiles" : 1,
      "totalNumberOfFilesIndexedByExtensions" : 0,
      "totalFilesSize" : 2070,
      "indexValueChangerEvaluationSpeed" : {
        "totalBytes" : 2070,
        "totalTime" : 84700
      },
      "snapshotInputMappingStats" : {
        "totalRequests" : 0,
        "totalMisses" : 0,
        "totalHits" : 0
      }
    }, {
      "indexId" : "Trigram.Index",
      "partOfTotalIndexingTime" : {
        "part" : 65600,
        "total" : 8537600
      },
      "totalNumberOfFiles" : 1,
      "totalNumberOfFilesIndexedByExtensions" : 0,
      "totalFilesSize" : 2070,
      "indexValueChangerEvaluationSpeed" : {
        "totalBytes" : 2070,
        "totalTime" : 65600
      },
      "snapshotInputMappingStats" : {
        "totalRequests" : 0,
        "totalMisses" : 0,
        "totalHits" : 0
      }
    } ],
    "scanningStatistics" : [ {
      "providerName" : "Refreshed files",
      "numberOfScannedFiles" : 8604,
      "numberOfSkippedFiles" : 0,
      "numberOfFilesForIndexing" : 8604,
      "numberOfFilesFullyIndexedByInfrastructureExtensions" : 0,
      "filesFullyIndexedByInfrastructureExtensions" : [ ],
      "statusTime" : 0,
      "scanningTime" : 598055700,
      "timeProcessingUpToDateFiles" : 0,
      "timeUpdatingContentLessIndexes" : 0,
      "timeIndexingWithoutContent" : 0,
      "roots" : [ "Not collected for refresh" ]
    } ],
    "fileProviderStatistics" : [ {
      "providerName" : "Refreshed files",
      "totalNumberOfIndexedFiles" : 8604,
      "totalNumberOfFilesFullyIndexedByExtensions" : 0,
      "totalIndexingVisibleTime" : 40813425200,
      "contentLoadingVisibleTime" : 3540512368,
      "numberOfTooLargeForIndexingFiles" : 0,
      "slowIndexedFiles" : [ ],
      "filesFullyIndexedByExtensions" : [ ],
      "isAppliedAllValuesSeparately" : true,
      "separateApplyingIndexesVisibleTime" : 19884324847
    } ],
    "visibleTimeToAllThreadTimeRatio" : 17.520471581806117
  }
}